main.py
test_main.py
short_url_cli-0.1.0.dist-info/METADATA
short_url_cli-0.1.0.dist-info/WHEEL
short_url_cli-0.1.0.dist-info/entry_points.txt
short_url_cli-0.1.0.dist-info/top_level.txt
short_url_cli-0.1.0.dist-info/RECORD
