Metadata-Version: 2.4
Name: short-url-cli
Version: 0.1.0
Summary: A fun and easy command-line tool for shortening URLs using TinyURL.
Author-email: Wayne Fagan <hello@waynefagan.dev>
Project-URL: Homepage, https://gitlab.com/Wayne-F/short-url-cli
Project-URL: Repository, https://gitlab.com/Wayne-F/short-url-cli
Keywords: url,shortener,cli,tinyurl,typer,rich
Classifier: Development Status :: 4 - Beta
Classifier: Intended Audience :: Developers
Classifier: Topic :: Internet :: WWW/HTTP
Classifier: Topic :: Utilities
Classifier: Programming Language :: Python :: 3
Classifier: Programming Language :: Python :: 3.9
Classifier: Programming Language :: Python :: 3.10
Classifier: Programming Language :: Python :: 3.11
Classifier: Programming Language :: Python :: 3.12
Classifier: License :: OSI Approved :: MIT License
Requires-Python: >=3.9
Requires-Dist: typer>=0.12.3
Requires-Dist: rich>=13.7.1
Requires-Dist: pyshorteners>=1.0.1
